figuremake/__init__.py
figuremake/main.py
figuremake-0.1.dist-info/LICENSE
figuremake-0.1.dist-info/METADATA
figuremake-0.1.dist-info/WHEEL
figuremake-0.1.dist-info/entry_points.txt
figuremake-0.1.dist-info/top_level.txt
figuremake-0.1.dist-info/RECORD
